{
	"type": "collection",
	"name": "demo4 changed",
	"id": "889219-8062b623-765b-446d-ad0b-54b715a2331d",
	"_attributes": {
		"flags": {
			"id": "8062b623-765b-446d-ad0b-54b715a2331d"
		}
	},
	"isPending": false,
	"isDeleting": false,
	"_foldersOrder": [],
	"_pendingFoldersOrder": [],
	"_order": [],
	"_pendingOrder": [],
	"initialVariables": null,
	"events": null,
	"auth": null,
	"protocolProfileBehavior": {},
	"description": null,
	"createdAt": "2022-08-11T14:05:41.000Z",
	"isForked": false,
	"isPublic": false,
	"isEditable": true,
	"isDeletable": true,
	"isArchived": false,
	"isFavorite": false,
	"isShareable": true,
	"userCanCreateMock": true,
	"userCanCreateMonitor": true,
	"owner": "889219",
	"foldersOrder": [],
	"order": [],
	"folders": [],
	"requests": [],
	"variables": null
}